ohm_ai/__init__.py
ohm_ai/client.py
ohm_ai/config.py
ohm_ai/filter.py
ohm_ai-1.0.1.dist-info/METADATA
ohm_ai-1.0.1.dist-info/WHEEL
ohm_ai-1.0.1.dist-info/licenses/LICENSE
ohm_ai-1.0.1.dist-info/RECORD
