Metadata-Version: 2.4
Name: ohm-ai
Version: 1.0.1
Summary: Python library to export data from and interact with the Ohm AI Platform
Author-email: Colin Chung <colin@ohm.ai>
License: Certain libraries contained in this file are subject to open source license requirements. Specifically:
License-File: LICENSE
Requires-Dist: gql[aiohttp,requests]>=3.5.2
Requires-Dist: pandas>=2.2.3
Requires-Dist: psycopg2-binary>=2.9
